i2c_lcd/__init__.py
i2c_lcd/i2c_lcd.py
i2c_lcd/lcd_api.py
i2c_lcd_esp32-0.0.19.dist-info/METADATA
i2c_lcd_esp32-0.0.19.dist-info/WHEEL
i2c_lcd_esp32-0.0.19.dist-info/top_level.txt
i2c_lcd_esp32-0.0.19.dist-info/RECORD
