Metadata-Version: 2.1
Name: i2c-lcd-esp32
Version: 0.0.19
Summary: i2c 16*2 lcd library for esp32 divkit v1
Home-page: UNKNOWN
Author: sami.moona
Author-email: <saminsx@gmail.com>
License: UNKNOWN
Keywords: i2c,lcd,16*2,esp32,divkit,wroom-32
Platform: UNKNOWN
Classifier: Development Status :: 1 - Planning
Classifier: Intended Audience :: Developers
Classifier: Programming Language :: Python :: 3
Classifier: Operating System :: Unix
Classifier: Operating System :: MacOS :: MacOS X
Classifier: Operating System :: Microsoft :: Windows
Classifier: Programming Language :: Python :: Implementation :: MicroPython
